deduckt/__init__.py
deduckt/ast_nodes.py
deduckt/deduckt.py
deduckt/generator.py
deduckt/main.py
deduckt/tracing.py
deduckt/type_system.py
python_deduckt-0.1.dist-info/METADATA
python_deduckt-0.1.dist-info/RECORD
python_deduckt-0.1.dist-info/WHEEL
python_deduckt-0.1.dist-info/entry_points.txt
python_deduckt-0.1.dist-info/top_level.txt
