Metadata-Version: 2.1
Name: python-deduckt
Version: 0.1
Summary: python-deduckt infers the concrete types used inside a python program and creates an AST database with static types. 
Home-page: https://www.metacraft-labs.com
Author: Metacraft Labs
Author-email: python@metacraft-labs.com
License: MIT
Platform: UNKNOWN
Classifier: Intended Audience :: Developers
Classifier: License :: OSI Approved :: MIT License
Classifier: Programming Language :: Python
Classifier: Programming Language :: Python :: 3
Classifier: Programming Language :: Python :: 3.3
Classifier: Programming Language :: Python :: 3.4
Classifier: Programming Language :: Python :: 3.5
Classifier: Programming Language :: Python :: 3.6
Classifier: Topic :: Software Development
Classifier: Topic :: Software Development :: Libraries :: Python Modules
Requires-Dist: pytest (==3.0.7)
Requires-Dist: colorama (==0.3.9)
